PygameUi/__init__.py
PygameUi/container.py
PygameUi/grid.py
PygameUi/image.py
PygameUi/label.py
PygameUi/layout.py
PygameUi/styles.py
PygameUi/widget.py
PygameUi/widget_checks.py
PygameUi/widget_tags.py
PygameUi/widget_types.py
PygameUi/window.py
pygame_ui_mb-0.1.1.dist-info/LICENSE
pygame_ui_mb-0.1.1.dist-info/METADATA
pygame_ui_mb-0.1.1.dist-info/WHEEL
pygame_ui_mb-0.1.1.dist-info/top_level.txt
pygame_ui_mb-0.1.1.dist-info/RECORD
