Metadata-Version: 2.1
Name: pygame-ui-mb
Version: 0.1.1
Summary: A package for fluid uis in PyGame
Home-page: https://github.com/Machine-builder/pygame-ui
Author: MACHINE_BUILDER
License: UNKNOWN
Project-URL: Bug Tracker, https://github.com/Machine-builder/pygame-ui/issues
Platform: UNKNOWN
Classifier: Programming Language :: Python :: 3
Classifier: License :: OSI Approved :: GNU General Public License v3 (GPLv3)
Classifier: Operating System :: OS Independent
Requires-Python: >=3.6
